MANIFEST.in
README.org
README.rst
lh-agpl3-LICENSE.txt
setup.py
./bin/mailMua-sysd.cs
./bin/qmail-inject-bisos.cs
./bin/qmail-remote-bisos.cs
./bin/qmailMua-admin.cs
./bin/qmailMua-assemble.cs
./bin/qmailMua-binsPrep.cs
bisos/__init__.py
bisos.qmailMua.egg-info/PKG-INFO
bisos.qmailMua.egg-info/SOURCES.txt
bisos.qmailMua.egg-info/dependency_links.txt
bisos.qmailMua.egg-info/not-zip-safe
bisos.qmailMua.egg-info/requires.txt
bisos.qmailMua.egg-info/top_level.txt
bisos/qmailMua/__init__.py
bisos/qmailMua/notqmailSysd.py
bisos/qmailMua/qmailInjectWrapper.py
bisos/qmailMua/qmailMuaAdmin.py
bisos/qmailMua/qmailMua_binsPrep.py
bisos/qmailMua/qmailRemoteWrapper.py